quickremi/__init__.py
quickremi/gui.py
ui/__init__.py
ui/creators.py
quickremi-1.1.dist-info/LICENSE
quickremi-1.1.dist-info/METADATA
quickremi-1.1.dist-info/WHEEL
quickremi-1.1.dist-info/top_level.txt
quickremi-1.1.dist-info/RECORD
