Metadata-Version: 2.1
Name: quickremi
Version: 1.1
Summary: A wrapper of REMI library to build UI front-ends purely using Python.
Author: Aru Raghuvanshi
Author-email: sixdigitco@gmail.com
Classifier: Programming Language :: Python :: 3
Classifier: License :: OSI Approved :: MIT License
Classifier: Operating System :: OS Independent
Requires-Python: >=3.7
License-File: LICENSE
Requires-Dist: remi
Requires-Dist: pytz
Requires-Dist: pandas
